openseespywin/LICENSE.md
openseespywin/__init__.py
openseespywin/opensees.pyd
openseespywin/lib/__init__.py
openseespywin-3.7.0.6.dist-info/METADATA
openseespywin-3.7.0.6.dist-info/WHEEL
openseespywin-3.7.0.6.dist-info/top_level.txt
openseespywin-3.7.0.6.dist-info/RECORD
