Metadata-Version: 2.1
Name: openseespywin
Version: 3.7.0.6
Summary: A OpenSeesPy Windows package
Home-page: https://github.com/zhuminjie/openseespy
Author: Minjie Zhu
Author-email: zhum@oregonstate.edu
License: LICENSE.md
Platform: Windows
Classifier: Programming Language :: Python :: 3.12
Classifier: Operating System :: Microsoft :: Windows
Requires-Python: ~= 3.12.0
